persistent_doc/__init__.py
persistent_doc/document.py
persistent_doc/transform.py
persistent_doc-0.5.1.dist-info/METADATA
persistent_doc-0.5.1.dist-info/WHEEL
persistent_doc-0.5.1.dist-info/top_level.txt
persistent_doc-0.5.1.dist-info/RECORD
