Metadata-Version: 2.1
Name: persistent-doc
Version: 0.5.1
Summary: An XML-like document with spreadsheet formulas for values and underlying persistent data structures
Home-page: https://github.com/asrp/persistent_doc
Author: asrp
Author-email: asrp@email.com
License: UNKNOWN
Keywords: persistent tree document formula
Platform: UNKNOWN
Requires-Dist: pyrsistent
